{"ts":1461671460296,"measurementOrder":[["ajax_ping,GET","observer/~dahora/allowed"],["ajax_ping,HEAD","observer/~dahora/someInvalidPath"],["ajax_ping,POST","observer/~dahora/allowed"],["ajax_ping,HEAD","observer/~dahora/disallowed"],["websocket_ping","observer:43234"],["ajax_ping,GET","172.16.0.1"],["ajax_ping,POST","observer/~dahora/disallowed"],["ajax_ping,GET","observer:1337"],["webrtc_ping","observer"],["ajax_ping,POST","172.16.0.1:1337"],["ajax_ping,HEAD","observer:1337"],["ajax_ping,POST","172.16.0.1"],["ajax_ping,GET","172.16.0.1:1337"],["ajax_ping,HEAD","172.16.0.1:1337"],["ajax_ping,POST","observer:1337"],["ajax_ping,GET","observer/~dahora/disallowed"],["ajax_ping,HEAD","172.16.0.1"],["ajax_ping,GET","observer/~dahora/someInvalidPath"],["webrtc_ping","imachine"],["ajax_ping,POST","observer/~dahora/someInvalidPath"],["ajax_ping,HEAD","observer/~dahora/allowed"]],"ajax_ping,GET,observer/~dahora/allowed":[{"ping":{"data":[{"seqNum":0,"difference":51.388},{"seqNum":1,"difference":51.604}],"time":1461671460296,"ping":true,"destination":"observer/~dahora/allowed","isBoss":true,"thing":"ajax_ping,GET"},"result":{"data":[{"seqNum":0,"batchNumber":64,"difference":111.38000000012107},{"seqNum":1,"batchNumber":64,"difference":57.72500000009313}],"time":1461671460296,"browser":"chrome","isBoss":true,"thing":"ajax_ping,GET","destination":"observer/~dahora/allowed"}},{"ping":{"data":[{"seqNum":0,"difference":51.2},{"seqNum":1,"difference":52.9}],"time":1461671460296,"ping":true,"destination":"observer/~dahora/allowed","isBoss":false,"thing":"ajax_ping,GET"},"result":{"data":[{"seqNum":0,"batchNumber":64,"difference":114.18000000016764},{"seqNum":1,"batchNumber":64,"difference":62.574999999953434}],"time":1461671460296,"browser":"chrome","isBoss":false,"thing":"ajax_ping,GET","destination":"observer/~dahora/allowed"}}],"ajax_ping,HEAD,observer/~dahora/someInvalidPath":[{"ping":{"data":[{"seqNum":0,"difference":51.227},{"seqNum":1,"difference":51.976}],"time":1461671460296,"ping":true,"destination":"observer/~dahora/someInvalidPath","isBoss":true,"thing":"ajax_ping,HEAD"},"result":{"data":[{"seqNum":0,"batchNumber":64,"difference":57.08499999996275},{"seqNum":1,"batchNumber":64,"difference":56.075000000186265}],"time":1461671460296,"browser":"chrome","isBoss":true,"thing":"ajax_ping,HEAD","destination":"observer/~dahora/someInvalidPath"}},{"ping":{"data":[{"seqNum":0,"difference":51},{"seqNum":1,"difference":51.2}],"time":1461671460296,"ping":true,"destination":"observer/~dahora/someInvalidPath","isBoss":false,"thing":"ajax_ping,HEAD"},"result":{"data":[{"seqNum":0,"batchNumber":64,"difference":72.57500000018626},{"seqNum":1,"batchNumber":64,"difference":59.704999999608845}],"time":1461671460296,"browser":"chrome","isBoss":false,"thing":"ajax_ping,HEAD","destination":"observer/~dahora/someInvalidPath"}}],"ajax_ping,POST,observer/~dahora/allowed":[{"ping":{"data":[{"seqNum":0,"difference":51.416},{"seqNum":1,"difference":51.574}],"time":1461671460296,"ping":true,"destination":"observer/~dahora/allowed","isBoss":true,"thing":"ajax_ping,POST"},"result":{"data":[{"seqNum":0,"batchNumber":64,"difference":57.04000000027008},{"seqNum":1,"batchNumber":64,"difference":57.49500000011176}],"time":1461671460296,"browser":"chrome","isBoss":true,"thing":"ajax_ping,POST","destination":"observer/~dahora/allowed"}},{"ping":{"data":[{"seqNum":0,"difference":51},{"seqNum":1,"difference":51.2}],"time":1461671460296,"ping":true,"destination":"observer/~dahora/allowed","isBoss":false,"thing":"ajax_ping,POST"},"result":{"data":[{"seqNum":0,"batchNumber":64,"difference":60.93000000016764},{"seqNum":1,"batchNumber":64,"difference":61.14999999990687}],"time":1461671460296,"browser":"chrome","isBoss":false,"thing":"ajax_ping,POST","destination":"observer/~dahora/allowed"}}],"ajax_ping,HEAD,observer/~dahora/disallowed":[{"ping":{"data":[{"seqNum":0,"difference":51.499},{"seqNum":1,"difference":51.365}],"time":1461671460296,"ping":true,"destination":"observer/~dahora/disallowed","isBoss":true,"thing":"ajax_ping,HEAD"},"result":{"data":[{"seqNum":0,"batchNumber":64,"difference":58.390000000130385},{"seqNum":1,"batchNumber":64,"difference":55.87000000011176}],"time":1461671460296,"browser":"chrome","isBoss":true,"thing":"ajax_ping,HEAD","destination":"observer/~dahora/disallowed"}},{"ping":{"data":[{"seqNum":0,"difference":51.4},{"seqNum":1,"difference":51.1}],"time":1461671460296,"ping":true,"destination":"observer/~dahora/disallowed","isBoss":false,"thing":"ajax_ping,HEAD"},"result":{"data":[{"seqNum":0,"batchNumber":64,"difference":63.19499999983236},{"seqNum":1,"batchNumber":64,"difference":58.9749999998603}],"time":1461671460296,"browser":"chrome","isBoss":false,"thing":"ajax_ping,HEAD","destination":"observer/~dahora/disallowed"}}],"websocket_ping,observer:43234":[{"ping":{"data":[{"seqNum":0,"difference":51.533},{"seqNum":1,"difference":51.586}],"time":1461671460296,"ping":true,"destination":"observer:43234","isBoss":true,"thing":"websocket_ping"},"result":{"data":[{"destination":"observer:43234","seqNum":0,"batchNumber":64,"difference":55.405},{"destination":"observer:43234","seqNum":1,"batchNumber":64,"difference":54.48}],"time":1461671460296,"browser":"chrome","isBoss":true,"thing":"websocket_ping","destination":"observer:43234"}},{"ping":{"data":[{"seqNum":0,"difference":51.1},{"seqNum":1,"difference":51.1}],"time":1461671460296,"ping":true,"destination":"observer:43234","isBoss":false,"thing":"websocket_ping"},"result":{"data":[{"destination":"observer:43234","seqNum":0,"batchNumber":64,"difference":54.99},{"destination":"observer:43234","seqNum":1,"batchNumber":64,"difference":54.515}],"time":1461671460296,"browser":"chrome","isBoss":false,"thing":"websocket_ping","destination":"observer:43234"}}],"ajax_ping,GET,172.16.0.1":[{"ping":{"data":[{"seqNum":0,"difference":1.168},{"seqNum":1,"difference":1.46}],"time":1461671460296,"ping":true,"destination":"172.16.0.1","isBoss":true,"thing":"ajax_ping,GET"},"result":{"data":[{"seqNum":0,"batchNumber":64,"difference":8.68999999971129},{"seqNum":1,"batchNumber":64,"difference":8.040000000037253}],"time":1461671460296,"browser":"chrome","isBoss":true,"thing":"ajax_ping,GET","destination":"172.16.0.1"}},{"ping":{"data":[{"seqNum":0,"difference":0.917},{"seqNum":1,"difference":0.883}],"time":1461671460296,"ping":true,"destination":"172.16.0.1","isBoss":false,"thing":"ajax_ping,GET"},"result":{"data":[{"seqNum":0,"batchNumber":64,"difference":22.765000000130385},{"seqNum":1,"batchNumber":64,"difference":10.789999999804422}],"time":1461671460296,"browser":"chrome","isBoss":false,"thing":"ajax_ping,GET","destination":"172.16.0.1"}}],"ajax_ping,POST,observer/~dahora/disallowed":[{"ping":{"data":[{"seqNum":0,"difference":51.396},{"seqNum":1,"difference":51.529}],"time":1461671460296,"ping":true,"destination":"observer/~dahora/disallowed","isBoss":true,"thing":"ajax_ping,POST"},"result":{"data":[{"seqNum":0,"batchNumber":64,"difference":57.514999999897555},{"seqNum":1,"batchNumber":64,"difference":56.95999999972992}],"time":1461671460296,"browser":"chrome","isBoss":true,"thing":"ajax_ping,POST","destination":"observer/~dahora/disallowed"}},{"ping":{"data":[{"seqNum":0,"difference":51.1},{"seqNum":1,"difference":51}],"time":1461671460296,"ping":true,"destination":"observer/~dahora/disallowed","isBoss":false,"thing":"ajax_ping,POST"},"result":{"data":[{"seqNum":0,"batchNumber":64,"difference":70.31999999983236},{"seqNum":1,"batchNumber":64,"difference":59.1999999997206}],"time":1461671460296,"browser":"chrome","isBoss":false,"thing":"ajax_ping,POST","destination":"observer/~dahora/disallowed"}}],"ajax_ping,GET,observer:1337":[{"ping":{"data":[{"seqNum":0,"difference":51.726},{"seqNum":1,"difference":51.664}],"time":1461671460296,"ping":true,"destination":"observer:1337","isBoss":true,"thing":"ajax_ping,GET"},"result":{"data":[{"seqNum":0,"batchNumber":64,"difference":56.55999999982305},{"seqNum":1,"batchNumber":64,"difference":54.37000000034459}],"time":1461671460296,"browser":"chrome","isBoss":true,"thing":"ajax_ping,GET","destination":"observer:1337"}},{"ping":{"data":[{"seqNum":0,"difference":51.3},{"seqNum":1,"difference":51.3}],"time":1461671460296,"ping":true,"destination":"observer:1337","isBoss":false,"thing":"ajax_ping,GET"},"result":{"data":[{"seqNum":0,"batchNumber":64,"difference":56.30500000016764},{"seqNum":1,"batchNumber":64,"difference":59.25500000012107}],"time":1461671460296,"browser":"chrome","isBoss":false,"thing":"ajax_ping,GET","destination":"observer:1337"}}],"webrtc_ping,observer":[{"ping":{"data":[{"seqNum":0,"difference":51.256},{"seqNum":1,"difference":51.613}],"time":1461671460296,"ping":true,"destination":"observer","isBoss":true,"thing":"webrtc_ping"},"result":{"data":[{"destination":"observer","text":"pong","seqNum":0,"batchNumber":64,"difference":5.81},{"destination":"observer","text":"pong","seqNum":1,"batchNumber":64,"difference":5.62}],"time":1461671460296,"browser":"chrome","isBoss":true,"thing":"webrtc_ping","destination":"observer"}},{"ping":{"data":[{"seqNum":0,"difference":51.2},{"seqNum":1,"difference":51.2}],"time":1461671460296,"ping":true,"destination":"observer","isBoss":false,"thing":"webrtc_ping"},"result":{"data":[{"destination":"observer","text":"pong","seqNum":0,"batchNumber":64,"difference":7},{"destination":"observer","text":"pong","seqNum":1,"batchNumber":64,"difference":6.295}],"time":1461671460296,"browser":"chrome","isBoss":false,"thing":"webrtc_ping","destination":"observer"}}],"ajax_ping,POST,172.16.0.1:1337":[{"ping":{"data":[{"seqNum":0,"difference":1.582},{"seqNum":1,"difference":1.338}],"time":1461671460296,"ping":true,"destination":"172.16.0.1:1337","isBoss":true,"thing":"ajax_ping,POST"},"result":{"data":[{"seqNum":0,"batchNumber":64,"difference":5.964999999618158},{"seqNum":1,"batchNumber":64,"difference":4.774999999906868}],"time":1461671460296,"browser":"chrome","isBoss":true,"thing":"ajax_ping,POST","destination":"172.16.0.1:1337"}},{"ping":{"data":[{"seqNum":0,"difference":0.959},{"seqNum":1,"difference":1.28}],"time":1461671460296,"ping":true,"destination":"172.16.0.1:1337","isBoss":false,"thing":"ajax_ping,POST"},"result":{"data":[{"seqNum":0,"batchNumber":64,"difference":6.5},{"seqNum":1,"batchNumber":64,"difference":5.955000000074506}],"time":1461671460296,"browser":"chrome","isBoss":false,"thing":"ajax_ping,POST","destination":"172.16.0.1:1337"}}],"ajax_ping,HEAD,observer:1337":[{"ping":{"data":[{"seqNum":0,"difference":51.596},{"seqNum":1,"difference":51.663}],"time":1461671460296,"ping":true,"destination":"observer:1337","isBoss":true,"thing":"ajax_ping,HEAD"},"result":{"data":[{"seqNum":0,"batchNumber":64,"difference":55.92999999993481},{"seqNum":1,"batchNumber":64,"difference":54.169999999925494}],"time":1461671460296,"browser":"chrome","isBoss":true,"thing":"ajax_ping,HEAD","destination":"observer:1337"}},{"ping":{"data":[{"seqNum":0,"difference":51.4},{"seqNum":1,"difference":51.2}],"time":1461671460296,"ping":true,"destination":"observer:1337","isBoss":false,"thing":"ajax_ping,HEAD"},"result":{"data":[{"seqNum":0,"batchNumber":64,"difference":55.51499999943189},{"seqNum":1,"batchNumber":64,"difference":56.480000000214204}],"time":1461671460296,"browser":"chrome","isBoss":false,"thing":"ajax_ping,HEAD","destination":"observer:1337"}}],"ajax_ping,POST,172.16.0.1":[{"ping":{"data":[{"seqNum":0,"difference":1.743},{"seqNum":1,"difference":1.375}],"time":1461671460296,"ping":true,"destination":"172.16.0.1","isBoss":true,"thing":"ajax_ping,POST"},"result":{"data":[{"seqNum":0,"batchNumber":64,"difference":6.084999999962747},{"seqNum":1,"batchNumber":64,"difference":7.079999999841675}],"time":1461671460296,"browser":"chrome","isBoss":true,"thing":"ajax_ping,POST","destination":"172.16.0.1"}},{"ping":{"data":[{"seqNum":0,"difference":0.954},{"seqNum":1,"difference":0.986}],"time":1461671460296,"ping":true,"destination":"172.16.0.1","isBoss":false,"thing":"ajax_ping,POST"},"result":{"data":[{"seqNum":0,"batchNumber":64,"difference":16.980000000214204},{"seqNum":1,"batchNumber":64,"difference":11.574999999953434}],"time":1461671460296,"browser":"chrome","isBoss":false,"thing":"ajax_ping,POST","destination":"172.16.0.1"}}],"ajax_ping,GET,172.16.0.1:1337":[{"ping":{"data":[{"seqNum":0,"difference":2.255},{"seqNum":1,"difference":1.433}],"time":1461671460296,"ping":true,"destination":"172.16.0.1:1337","isBoss":true,"thing":"ajax_ping,GET"},"result":{"data":[{"seqNum":0,"batchNumber":64,"difference":4.300000000046566},{"seqNum":1,"batchNumber":64,"difference":4.28000000026077}],"time":1461671460296,"browser":"chrome","isBoss":true,"thing":"ajax_ping,GET","destination":"172.16.0.1:1337"}},{"ping":{"data":[{"seqNum":0,"difference":0.94},{"seqNum":1,"difference":0.919}],"time":1461671460296,"ping":true,"destination":"172.16.0.1:1337","isBoss":false,"thing":"ajax_ping,GET"},"result":{"data":[{"seqNum":0,"batchNumber":64,"difference":17.62999999988824},{"seqNum":1,"batchNumber":64,"difference":6.375000000232831}],"time":1461671460296,"browser":"chrome","isBoss":false,"thing":"ajax_ping,GET","destination":"172.16.0.1:1337"}}],"ajax_ping,HEAD,172.16.0.1:1337":[{"ping":{"data":[{"seqNum":0,"difference":1.405},{"seqNum":1,"difference":1.856}],"time":1461671460296,"ping":true,"destination":"172.16.0.1:1337","isBoss":true,"thing":"ajax_ping,HEAD"},"result":{"data":[{"seqNum":0,"batchNumber":64,"difference":3.7600000000093132},{"seqNum":1,"batchNumber":64,"difference":3.7500000004656613}],"time":1461671460296,"browser":"chrome","isBoss":true,"thing":"ajax_ping,HEAD","destination":"172.16.0.1:1337"}},{"ping":{"data":[{"seqNum":0,"difference":0.935},{"seqNum":1,"difference":0.847}],"time":1461671460296,"ping":true,"destination":"172.16.0.1:1337","isBoss":false,"thing":"ajax_ping,HEAD"},"result":{"data":[{"seqNum":0,"batchNumber":64,"difference":8.705000000307336},{"seqNum":1,"batchNumber":64,"difference":6.3950000000186265}],"time":1461671460296,"browser":"chrome","isBoss":false,"thing":"ajax_ping,HEAD","destination":"172.16.0.1:1337"}}],"ajax_ping,POST,observer:1337":[{"ping":{"data":[{"seqNum":0,"difference":51.901},{"seqNum":1,"difference":51.74}],"time":1461671460296,"ping":true,"destination":"observer:1337","isBoss":true,"thing":"ajax_ping,POST"},"result":{"data":[{"seqNum":0,"batchNumber":64,"difference":56.6750000002794},{"seqNum":1,"batchNumber":64,"difference":54.19500000006519}],"time":1461671460296,"browser":"chrome","isBoss":true,"thing":"ajax_ping,POST","destination":"observer:1337"}},{"ping":{"data":[{"seqNum":0,"difference":51},{"seqNum":1,"difference":51.1}],"time":1461671460296,"ping":true,"destination":"observer:1337","isBoss":false,"thing":"ajax_ping,POST"},"result":{"data":[{"seqNum":0,"batchNumber":64,"difference":67.07999999960884},{"seqNum":1,"batchNumber":64,"difference":56.38000000012107}],"time":1461671460296,"browser":"chrome","isBoss":false,"thing":"ajax_ping,POST","destination":"observer:1337"}}],"ajax_ping,GET,observer/~dahora/disallowed":[{"ping":{"data":[{"seqNum":0,"difference":51.552},{"seqNum":1,"difference":51.329}],"time":1461671460296,"ping":true,"destination":"observer/~dahora/disallowed","isBoss":true,"thing":"ajax_ping,GET"},"result":{"data":[{"seqNum":0,"batchNumber":64,"difference":110.63000000012107},{"seqNum":1,"batchNumber":64,"difference":56.51000000000931}],"time":1461671460296,"browser":"chrome","isBoss":true,"thing":"ajax_ping,GET","destination":"observer/~dahora/disallowed"}},{"ping":{"data":[{"seqNum":0,"difference":51.5},{"seqNum":1,"difference":51.2}],"time":1461671460296,"ping":true,"destination":"observer/~dahora/disallowed","isBoss":false,"thing":"ajax_ping,GET"},"result":{"data":[{"seqNum":0,"batchNumber":64,"difference":113.51000000024214},{"seqNum":1,"batchNumber":64,"difference":60.235000000102445}],"time":1461671460296,"browser":"chrome","isBoss":false,"thing":"ajax_ping,GET","destination":"observer/~dahora/disallowed"}}],"ajax_ping,HEAD,172.16.0.1":[{"ping":{"data":[{"seqNum":0,"difference":1.232},{"seqNum":1,"difference":1.586}],"time":1461671460296,"ping":true,"destination":"172.16.0.1","isBoss":true,"thing":"ajax_ping,HEAD"},"result":{"data":[{"seqNum":0,"batchNumber":64,"difference":9.055000000167638},{"seqNum":1,"batchNumber":64,"difference":6.505000000353903}],"time":1461671460296,"browser":"chrome","isBoss":true,"thing":"ajax_ping,HEAD","destination":"172.16.0.1"}},{"ping":{"data":[{"seqNum":0,"difference":2.76},{"seqNum":1,"difference":1.13}],"time":1461671460296,"ping":true,"destination":"172.16.0.1","isBoss":false,"thing":"ajax_ping,HEAD"},"result":{"data":[{"seqNum":0,"batchNumber":64,"difference":23.415000000037253},{"seqNum":1,"batchNumber":64,"difference":12.144999999552965}],"time":1461671460296,"browser":"chrome","isBoss":false,"thing":"ajax_ping,HEAD","destination":"172.16.0.1"}}],"ajax_ping,GET,observer/~dahora/someInvalidPath":[{"ping":{"data":[{"seqNum":0,"difference":51.494},{"seqNum":1,"difference":52.061}],"time":1461671460296,"ping":true,"destination":"observer/~dahora/someInvalidPath","isBoss":true,"thing":"ajax_ping,GET"},"result":{"data":[{"seqNum":0,"batchNumber":64,"difference":57.55499999970198},{"seqNum":1,"batchNumber":64,"difference":57.65000000037253}],"time":1461671460296,"browser":"chrome","isBoss":true,"thing":"ajax_ping,GET","destination":"observer/~dahora/someInvalidPath"}},{"ping":{"data":[{"seqNum":0,"difference":51.6},{"seqNum":1,"difference":51.9}],"time":1461671460296,"ping":true,"destination":"observer/~dahora/someInvalidPath","isBoss":false,"thing":"ajax_ping,GET"},"result":{"data":[{"seqNum":0,"batchNumber":64,"difference":60.450000000186265},{"seqNum":1,"batchNumber":64,"difference":61.385000000242144}],"time":1461671460296,"browser":"chrome","isBoss":false,"thing":"ajax_ping,GET","destination":"observer/~dahora/someInvalidPath"}}],"webrtc_ping,imachine":[{"ping":{"data":[{"seqNum":0,"difference":0.052},{"seqNum":1,"difference":0.104}],"time":1461671460296,"ping":true,"destination":"imachine","isBoss":true,"thing":"webrtc_ping"},"result":{"data":[{"destination":"imachine","text":"pong","seqNum":0,"batchNumber":64,"difference":18.86},{"destination":"imachine","text":"pong","seqNum":1,"batchNumber":64,"difference":6.01}],"time":1461671460296,"browser":"chrome","isBoss":true,"thing":"webrtc_ping","destination":"imachine"}},{"ping":{"data":[{"seqNum":0,"difference":1.59},{"seqNum":1,"difference":1.74}],"time":1461671460296,"ping":true,"destination":"imachine","isBoss":false,"thing":"webrtc_ping"},"result":{"data":[{"destination":"imachine","text":"pong","seqNum":0,"batchNumber":64,"difference":5.41},{"destination":"imachine","text":"pong","seqNum":1,"batchNumber":64,"difference":4.685}],"time":1461671460296,"browser":"chrome","isBoss":false,"thing":"webrtc_ping","destination":"imachine"}}],"ajax_ping,POST,observer/~dahora/someInvalidPath":[{"ping":{"data":[{"seqNum":0,"difference":51.34},{"seqNum":1,"difference":51.437}],"time":1461671460296,"ping":true,"destination":"observer/~dahora/someInvalidPath","isBoss":true,"thing":"ajax_ping,POST"},"result":{"data":[{"seqNum":0,"batchNumber":64,"difference":56.580000000074506},{"seqNum":1,"batchNumber":64,"difference":57.08499999996275}],"time":1461671460296,"browser":"chrome","isBoss":true,"thing":"ajax_ping,POST","destination":"observer/~dahora/someInvalidPath"}},{"ping":{"data":[{"seqNum":0,"difference":51.3},{"seqNum":1,"difference":51.2}],"time":1461671460296,"ping":true,"destination":"observer/~dahora/someInvalidPath","isBoss":false,"thing":"ajax_ping,POST"},"result":{"data":[{"seqNum":0,"batchNumber":64,"difference":93.95999999996275},{"seqNum":1,"batchNumber":64,"difference":58.795000000391155}],"time":1461671460296,"browser":"chrome","isBoss":false,"thing":"ajax_ping,POST","destination":"observer/~dahora/someInvalidPath"}}],"ajax_ping,HEAD,observer/~dahora/allowed":[{"ping":{"data":[{"seqNum":0,"difference":51.49},{"seqNum":1,"difference":51.652}],"time":1461671460296,"ping":true,"destination":"observer/~dahora/allowed","isBoss":true,"thing":"ajax_ping,HEAD"},"result":{"data":[{"seqNum":0,"batchNumber":64,"difference":56.87000000011176},{"seqNum":1,"batchNumber":64,"difference":56.87999999988824}],"time":1461671460296,"browser":"chrome","isBoss":true,"thing":"ajax_ping,HEAD","destination":"observer/~dahora/allowed"}},{"ping":{"data":[{"seqNum":0,"difference":51.2},{"seqNum":1,"difference":51.1}],"time":1461671460296,"ping":true,"destination":"observer/~dahora/allowed","isBoss":false,"thing":"ajax_ping,HEAD"},"result":{"data":[{"seqNum":0,"batchNumber":64,"difference":59.81000000005588},{"seqNum":1,"batchNumber":64,"difference":60.83999999985099}],"time":1461671460296,"browser":"chrome","isBoss":false,"thing":"ajax_ping,HEAD","destination":"observer/~dahora/allowed"}}]}